Passenger_flow_OD_chart_RunningTrainsPlot/__init__.py
Passenger_flow_OD_chart_RunningTrainsPlot/main.py
Passenger_flow_OD_chart_RunningTrainsPlot-2024.0.5.dist-info/LICENSE
Passenger_flow_OD_chart_RunningTrainsPlot-2024.0.5.dist-info/METADATA
Passenger_flow_OD_chart_RunningTrainsPlot-2024.0.5.dist-info/WHEEL
Passenger_flow_OD_chart_RunningTrainsPlot-2024.0.5.dist-info/top_level.txt
Passenger_flow_OD_chart_RunningTrainsPlot-2024.0.5.dist-info/RECORD
