Metadata-Version: 2.1
Name: Passenger_flow_OD_chart_RunningTrainsPlot
Version: 2024.0.5
Summary: An open-source library for visualizing transportation data
Author-email: ZeyuShen <sc22zs2@leeds.ac.uk>
Requires-Python: >=3.8
License-File: LICENSE
Requires-Dist: pandas
Requires-Dist: matplotlib
Requires-Dist: numpy
